{
    "id": "9a1f874d-206d-40f1-bc3d-cc0d800e757f",
    "title": "ALPM_Boring",
    "content": [
        {
            "type": "text",
            "data": "Boring"
        },
        {
            "type": "image",
            "data": "image2062.gif",
            "description": "[Placeholder for AI-generated description]"
        },
        {
            "type": "image",
            "data": "image936.gif",
            "description": "[Placeholder for AI-generated description]"
        },
        {
            "type": "text",
            "data": "The Boring Tab at Cabinet Properties has twelve options:"
        },
        {
            "type": "text",
            "data": "Boring Style -  This option allows you to choose the type of Line Boring the selected Assembly will use. There are four options:"
        },
        {
            "type": "text",
            "data": "Boring Style -  This option allows you to choose the type of Line Boring the selected Assembly will use. There are four options:"
        },
        {
            "type": "text",
            "data": "Boring Style -  This option allows you to choose the type of Line Boring the selected Assembly will use. There are four options:"
        },
        {
            "type": "image",
            "data": "image1258.gif",
            "description": "[Placeholder for AI-generated description]"
        },
        {
            "type": "text",
            "data": "No Boring Holes - Will remove all Line Boring from the selected Assembly. \n \n \n Bore All Holes - Will \"Bore All Holes\" (Shotgun Line Bore) the selected Assembly. \n \n \n Bore Only Required Holes - Will \"Bore Only Required Holed\" for the selected Assembly. \n \n \n Bore By Opening - Will \"Bore By Opening\" the selected Assembly."
        },
        {
            "type": "text",
            "data": "No Boring Holes - Will remove all Line Boring from the selected Assembly."
        },
        {
            "type": "text",
            "data": "No Boring Holes - Will remove all Line Boring from the selected Assembly."
        },
        {
            "type": "text",
            "data": "Bore All Holes - Will \"Bore All Holes\" (Shotgun Line Bore) the selected Assembly."
        },
        {
            "type": "text",
            "data": "Bore All Holes - Will \"Bore All Holes\" (Shotgun Line Bore) the selected Assembly."
        },
        {
            "type": "text",
            "data": "Bore Only Required Holes - Will \"Bore Only Required Holed\" for the selected Assembly."
        },
        {
            "type": "text",
            "data": "Bore Only Required Holes - Will \"Bore Only Required Holed\" for the selected Assembly."
        },
        {
            "type": "text",
            "data": "Bore By Opening - Will \"Bore By Opening\" the selected Assembly."
        },
        {
            "type": "text",
            "data": "Bore By Opening - Will \"Bore By Opening\" the selected Assembly."
        },
        {
            "type": "text",
            "data": "You must have the Assembly Wizard fully configured for each of these options in order to get good results."
        },
        {
            "type": "image",
            "data": "Information.png",
            "description": "[Placeholder for AI-generated description]"
        },
        {
            "type": "text",
            "data": "Balanced Panels -  Use this option to specify whether you want your  Line Boring  to be equally spaced from the Top and Bottom of your End Panels. See image below:"
        },
        {
            "type": "text",
            "data": "Balanced Panels -  Use this option to specify whether you want your  Line Boring  to be equally spaced from the Top and Bottom of your End Panels. See image below:"
        },
        {
            "type": "text",
            "data": "Balanced Panels -  Use this option to specify whether you want your  Line Boring  to be equally spaced from the Top and Bottom of your End Panels. See image below:"
        },
        {
            "type": "link",
            "data": {
                "text": "Line Boring",
                "uuid": "8a6d2bd9-6fae-4748-9e0a-304d3756ae40",
                "description": "[Placeholder for AI-generated description]"
            }
        },
        {
            "type": "image",
            "data": "image35111.gif",
            "description": "[Placeholder for AI-generated description]"
        },
        {
            "type": "text",
            "data": "Balanced Openings -  Use this option to specify whether you want your Line Boring, if set to Bore By Opening, to be equally spaced from the top and bottom of the Opening."
        },
        {
            "type": "text",
            "data": "Balanced Openings -  Use this option to specify whether you want your Line Boring, if set to Bore By Opening, to be equally spaced from the top and bottom of the Opening."
        },
        {
            "type": "text",
            "data": "Balanced Openings -  Use this option to specify whether you want your Line Boring, if set to Bore By Opening, to be equally spaced from the top and bottom of the Opening."
        },
        {
            "type": "text",
            "data": "Align Reveals to System Holes -  Use this option to specify whether you want your  Reveals  to align with you  Line Boring . See image below:"
        },
        {
            "type": "text",
            "data": "Align Reveals to System Holes -  Use this option to specify whether you want your  Reveals  to align with you  Line Boring . See image below:"
        },
        {
            "type": "text",
            "data": "Align Reveals to System Holes -  Use this option to specify whether you want your  Reveals  to align with you  Line Boring . See image below:"
        },
        {
            "type": "link",
            "data": {
                "text": "Reveals",
                "uuid": "3a33e00e-182e-449d-8fa0-b3e602a017ef",
                "description": "[Placeholder for AI-generated description]"
            }
        },
        {
            "type": "link",
            "data": {
                "text": "Line Boring",
                "uuid": "f4396e91-e17d-4f7a-b7db-fb84fe53ef3a",
                "description": "[Placeholder for AI-generated description]"
            }
        },
        {
            "type": "image",
            "data": "image352.gif",
            "description": "[Placeholder for AI-generated description]"
        },
        {
            "type": "text",
            "data": "Top Construction Holes -  You can use this option to turn off Top  Construction Boring . \n \n \n Bottom Construction Holes -  You can use this option to turn off Bottom  Construction Boring . \n \n \n Align Shelves to System Holes -  Use this option to specify whether you want your  Adjustable Shelves  to align with your  Line Boring . \n \n \n First Hole Location -  This sets the location for the first  Line Boring  hole vertically. \n \n \n Line Bore Hole Depth -  This sets the Depth of  Line Bores . \n \n \n Line Bore Hole Diameter -  This sets the Diameter of  Line Bores . \n \n \n Front Line Bore Set-back -  Sets the Front  Line Bore \u00a0setback for the active Assembly. The reference side (Front or Back) is controlled in the Construction Method selected for the active Assembly. \n \n \n Rear Line Bore Set-back -  Sets the Rear  Line Bore \u00a0setback for the active Assembly. The reference side (Front or Back) is controlled in the Construction Method selected for the active Assembly."
        },
        {
            "type": "text",
            "data": "Top Construction Holes -  You can use this option to turn off Top  Construction Boring ."
        },
        {
            "type": "text",
            "data": "Top Construction Holes -  You can use this option to turn off Top  Construction Boring ."
        },
        {
            "type": "link",
            "data": {
                "text": "Construction Boring",
                "uuid": "3e23e9ca-3aa4-4df6-8da6-78640aba9721",
                "description": "[Placeholder for AI-generated description]"
            }
        },
        {
            "type": "text",
            "data": "Bottom Construction Holes -  You can use this option to turn off Bottom  Construction Boring ."
        },
        {
            "type": "text",
            "data": "Bottom Construction Holes -  You can use this option to turn off Bottom  Construction Boring ."
        },
        {
            "type": "link",
            "data": {
                "text": "Construction Boring",
                "uuid": "3e23e9ca-3aa4-4df6-8da6-78640aba9721",
                "description": "[Placeholder for AI-generated description]"
            }
        },
        {
            "type": "text",
            "data": "Align Shelves to System Holes -  Use this option to specify whether you want your  Adjustable Shelves  to align with your  Line Boring ."
        },
        {
            "type": "text",
            "data": "Align Shelves to System Holes -  Use this option to specify whether you want your  Adjustable Shelves  to align with your  Line Boring ."
        },
        {
            "type": "link",
            "data": {
                "text": "Adjustable Shelves",
                "uuid": "9d870f4e-b767-4baa-a1dc-012dff55d89e",
                "description": "[Placeholder for AI-generated description]"
            }
        },
        {
            "type": "link",
            "data": {
                "text": "Line Boring",
                "uuid": "8a6d2bd9-6fae-4748-9e0a-304d3756ae40",
                "description": "[Placeholder for AI-generated description]"
            }
        },
        {
            "type": "text",
            "data": "First Hole Location -  This sets the location for the first  Line Boring  hole vertically."
        },
        {
            "type": "text",
            "data": "First Hole Location -  This sets the location for the first  Line Boring  hole vertically."
        },
        {
            "type": "link",
            "data": {
                "text": "Line Boring",
                "uuid": "8a6d2bd9-6fae-4748-9e0a-304d3756ae40",
                "description": "[Placeholder for AI-generated description]"
            }
        },
        {
            "type": "text",
            "data": "Line Bore Hole Depth -  This sets the Depth of  Line Bores ."
        },
        {
            "type": "text",
            "data": "Line Bore Hole Depth -  This sets the Depth of  Line Bores ."
        },
        {
            "type": "link",
            "data": {
                "text": "Line Bores",
                "uuid": "8a6d2bd9-6fae-4748-9e0a-304d3756ae40",
                "description": "[Placeholder for AI-generated description]"
            }
        },
        {
            "type": "text",
            "data": "Line Bore Hole Diameter -  This sets the Diameter of  Line Bores ."
        },
        {
            "type": "text",
            "data": "Line Bore Hole Diameter -  This sets the Diameter of  Line Bores ."
        },
        {
            "type": "link",
            "data": {
                "text": "Line Bores",
                "uuid": "8a6d2bd9-6fae-4748-9e0a-304d3756ae40",
                "description": "[Placeholder for AI-generated description]"
            }
        },
        {
            "type": "text",
            "data": "Front Line Bore Set-back -  Sets the Front  Line Bore \u00a0setback for the active Assembly. The reference side (Front or Back) is controlled in the Construction Method selected for the active Assembly."
        },
        {
            "type": "text",
            "data": "Front Line Bore Set-back -  Sets the Front  Line Bore \u00a0setback for the active Assembly. The reference side (Front or Back) is controlled in the Construction Method selected for the active Assembly."
        },
        {
            "type": "link",
            "data": {
                "text": "Line Bore",
                "uuid": "8a6d2bd9-6fae-4748-9e0a-304d3756ae40",
                "description": "[Placeholder for AI-generated description]"
            }
        },
        {
            "type": "text",
            "data": "Rear Line Bore Set-back -  Sets the Rear  Line Bore \u00a0setback for the active Assembly. The reference side (Front or Back) is controlled in the Construction Method selected for the active Assembly."
        },
        {
            "type": "text",
            "data": "Rear Line Bore Set-back -  Sets the Rear  Line Bore \u00a0setback for the active Assembly. The reference side (Front or Back) is controlled in the Construction Method selected for the active Assembly."
        },
        {
            "type": "link",
            "data": {
                "text": "Line Bore",
                "uuid": "8a6d2bd9-6fae-4748-9e0a-304d3756ae40",
                "description": "[Placeholder for AI-generated description]"
            }
        },
        {
            "type": "text",
            "data": "Remember changes made here will only affect the current Assembly. Also, changes made here are attached as permanent (unless you remove them) overrides on the Assembly; which means that if you Save this Assembly into a Catalog these overrides will also be Saved."
        },
        {
            "type": "image",
            "data": "Warning.png",
            "description": "[Placeholder for AI-generated description]"
        }
    ],
    "source_file": "CVEnglish_Essential\\Assembly_Level\\Ribbonbar\\Main_Tab\\Properties_Group\\ALPM_Boring.htm",
    "version": "2024",
    "source_type": "help_file"
}