{
    "id": "85359780-bc15-467a-bdd5-6f907270265c",
    "title": "ALPM_Hardware",
    "content": [
        {
            "type": "text",
            "data": "Top \n > \n \n \n Assembly Level \n > \n \n Ribbonbar \n > \n \n Main Tab \n > \n \n Properties Group \n > \n \n Hardware"
        },
        {
            "type": "text",
            "data": "Top \n >"
        },
        {
            "type": "text",
            "data": "Assembly Level \n >"
        },
        {
            "type": "link",
            "data": {
                "text": "Assembly Level",
                "uuid": "b0552ea2-b430-4836-aa5e-42dfd04f9eda",
                "description": "[Placeholder for AI-generated description]"
            }
        },
        {
            "type": "text",
            "data": "Ribbonbar \n >"
        },
        {
            "type": "link",
            "data": {
                "text": "Ribbonbar",
                "uuid": "a095688d-3b5c-4aba-8f35-bdc4541dcc7f",
                "description": "[Placeholder for AI-generated description]"
            }
        },
        {
            "type": "text",
            "data": "Main Tab \n >"
        },
        {
            "type": "link",
            "data": {
                "text": "Main Tab",
                "uuid": "a095688d-3b5c-4aba-8f35-bdc4541dcc7f",
                "description": "[Placeholder for AI-generated description]"
            }
        },
        {
            "type": "text",
            "data": "Properties Group \n >"
        },
        {
            "type": "link",
            "data": {
                "text": "Properties Group",
                "uuid": "6f52466f-ffa6-4f56-b4cd-6f5da81e612d",
                "description": "[Placeholder for AI-generated description]"
            }
        },
        {
            "type": "text",
            "data": "Hardware"
        },
        {
            "type": "text",
            "data": "Hardware"
        },
        {
            "type": "text",
            "data": "Hardware"
        },
        {
            "type": "image",
            "data": "image2057.gif",
            "description": "[Placeholder for AI-generated description]"
        },
        {
            "type": "image",
            "data": "image932.gif",
            "description": "[Placeholder for AI-generated description]"
        },
        {
            "type": "text",
            "data": "The Hardware Tab at Cabinet Properties has the following options:"
        },
        {
            "type": "text",
            "data": "Pull Schedule -  Allows you to specify the  Pulls Material Schedule  to use with the active Assembly. \n \n \n Drawer Guide Schedule -  Allows you to specify the  Drawer Guides Material Schedule  to use with the active Assembly. \n \n \n Hinge Schedule -  Allows you to specify the  Hinges Material Schedule  to use with the active Assembly. \n \n \n Beaded Frames Bead Profile -   -  This option is only available if a Hinge Schedule utilizing an Inset Hinge is selected. This option allows you to specify the Bead Profile to utilize if doing a Beaded Face Frame Construction. If you are not doing a Beaded Face Frame Construction do not select a Bead Profile. \n \n \n Sliding Door Rail Schedule -  Allows you to specify the  Sliding Door Rails Schedule  to use with the active Assembly."
        },
        {
            "type": "text",
            "data": "Pull Schedule -  Allows you to specify the  Pulls Material Schedule  to use with the active Assembly."
        },
        {
            "type": "text",
            "data": "Pull Schedule -  Allows you to specify the  Pulls Material Schedule  to use with the active Assembly."
        },
        {
            "type": "link",
            "data": {
                "text": "Pulls Material Schedule",
                "uuid": "a465c0a1-6368-4a1c-a3ca-7464612d29bc",
                "description": "[Placeholder for AI-generated description]"
            }
        },
        {
            "type": "text",
            "data": "Drawer Guide Schedule -  Allows you to specify the  Drawer Guides Material Schedule  to use with the active Assembly."
        },
        {
            "type": "text",
            "data": "Drawer Guide Schedule -  Allows you to specify the  Drawer Guides Material Schedule  to use with the active Assembly."
        },
        {
            "type": "link",
            "data": {
                "text": "Drawer Guides Material Schedule",
                "uuid": "8596e3db-054a-4eb9-b724-6b6fca567e27",
                "description": "[Placeholder for AI-generated description]"
            }
        },
        {
            "type": "text",
            "data": "Hinge Schedule -  Allows you to specify the  Hinges Material Schedule  to use with the active Assembly."
        },
        {
            "type": "text",
            "data": "Hinge Schedule -  Allows you to specify the  Hinges Material Schedule  to use with the active Assembly."
        },
        {
            "type": "link",
            "data": {
                "text": "Hinges Material Schedule",
                "uuid": "5ce8230a-842f-456f-9f66-3b5f7ae45be7",
                "description": "[Placeholder for AI-generated description]"
            }
        },
        {
            "type": "text",
            "data": "Beaded Frames Bead Profile -   -  This option is only available if a Hinge Schedule utilizing an Inset Hinge is selected. This option allows you to specify the Bead Profile to utilize if doing a Beaded Face Frame Construction. If you are not doing a Beaded Face Frame Construction do not select a Bead Profile."
        },
        {
            "type": "text",
            "data": "Beaded Frames Bead Profile -   -  This option is only available if a Hinge Schedule utilizing an Inset Hinge is selected. This option allows you to specify the Bead Profile to utilize if doing a Beaded Face Frame Construction. If you are not doing a Beaded Face Frame Construction do not select a Bead Profile."
        },
        {
            "type": "image",
            "data": "S2M.jpg",
            "description": "[Placeholder for AI-generated description]"
        },
        {
            "type": "text",
            "data": "Sliding Door Rail Schedule -  Allows you to specify the  Sliding Door Rails Schedule  to use with the active Assembly."
        },
        {
            "type": "text",
            "data": "Sliding Door Rail Schedule -  Allows you to specify the  Sliding Door Rails Schedule  to use with the active Assembly."
        },
        {
            "type": "link",
            "data": {
                "text": "Sliding Door Rails Schedule",
                "uuid": "1124e2f5-b1d8-49d7-a0ca-e7f455171ee7",
                "description": "[Placeholder for AI-generated description]"
            }
        },
        {
            "type": "text",
            "data": "Remember changes made here will only affect the current Assembly. Also, changes made here are attached as permanent (unless you remove them) overrides on the Assembly; which means that if you Save this Assembly into a Catalog these overrides will also be Saved."
        },
        {
            "type": "image",
            "data": "Warning.png",
            "description": "[Placeholder for AI-generated description]"
        }
    ],
    "source_file": "CVEnglish_Essential\\Assembly_Level\\Ribbonbar\\Main_Tab\\Properties_Group\\ALPM_Hardware.htm",
    "version": "2024",
    "source_type": "help_file"
}